jupyterlab_mlflow/__init__.py
jupyterlab_mlflow/_version.py
jupyterlab_mlflow/post_install.py
jupyterlab_mlflow/schema/plugin.json
jupyterlab_mlflow/serverextension/__init__.py
jupyterlab_mlflow/serverextension/handlers.py
jupyterlab_mlflow/serverextension/mlflow_server.py
jupyterlab_mlflow-0.5.0.data/data/etc/jupyter/jupyter_server_config.d/jupyterlab_mlflow.json
jupyterlab_mlflow-0.5.0.data/data/share/jupyter/labextensions/jupyterlab-mlflow/package.json
jupyterlab_mlflow-0.5.0.data/data/share/jupyter/labextensions/jupyterlab-mlflow/schemas/jupyterlab-mlflow/package.json.orig
jupyterlab_mlflow-0.5.0.data/data/share/jupyter/labextensions/jupyterlab-mlflow/schemas/jupyterlab-mlflow/plugin.json
jupyterlab_mlflow-0.5.0.data/data/share/jupyter/labextensions/jupyterlab-mlflow/static/218.c52b5bfb00387250d0e2.js
jupyterlab_mlflow-0.5.0.data/data/share/jupyter/labextensions/jupyterlab-mlflow/static/665.f3ea36ea04224fd9c2f3.js
jupyterlab_mlflow-0.5.0.data/data/share/jupyter/labextensions/jupyterlab-mlflow/static/remoteEntry.dc8ea247b926418f1427.js
jupyterlab_mlflow-0.5.0.data/data/share/jupyter/labextensions/jupyterlab-mlflow/static/style.js
jupyterlab_mlflow-0.5.0.data/data/share/jupyter/labextensions/jupyterlab-mlflow/static/third-party-licenses.json
jupyterlab_mlflow-0.5.0.data/data/share/jupyter/labextensions/jupyterlab-mlflow/install.json
jupyterlab_mlflow-0.5.0.data/data/share/jupyter/labextensions/jupyterlab-mlflow/schema/plugin.json
jupyterlab_mlflow-0.5.0.dist-info/METADATA
jupyterlab_mlflow-0.5.0.dist-info/WHEEL
jupyterlab_mlflow-0.5.0.dist-info/entry_points.txt
jupyterlab_mlflow-0.5.0.dist-info/licenses/LICENSE
jupyterlab_mlflow-0.5.0.dist-info/RECORD
