Metadata-Version: 2.4
Name: jupyterlab-mlflow
Version: 0.5.0
Project-URL: Homepage, https://github.com/BioLM/jupyterlab-mlflow
Project-URL: Bug Tracker, https://github.com/BioLM/jupyterlab-mlflow/issues
Project-URL: Documentation, https://github.com/BioLM/jupyterlab-mlflow#readme
Project-URL: Source, https://github.com/BioLM/jupyterlab-mlflow
Author: JupyterLab MLflow Contributors
License: BSD 3-Clause License
License-File: LICENSE
Keywords: Jupyter,JupyterLab,MLflow,jupyterlab-extension
Classifier: Framework :: Jupyter
Classifier: Framework :: Jupyter :: JupyterLab
Classifier: Framework :: Jupyter :: JupyterLab :: 4
Classifier: License :: OSI Approved :: BSD License
Classifier: Programming Language :: Python
Classifier: Programming Language :: Python :: 3
Classifier: Programming Language :: Python :: 3.8
Classifier: Programming Language :: Python :: 3.9
Classifier: Programming Language :: Python :: 3.10
Classifier: Programming Language :: Python :: 3.11
Requires-Python: >=3.8
Requires-Dist: jupyterlab<5,>=4.0.0
Requires-Dist: mlflow>=2.0.0
Requires-Dist: tornado>=6.0.0
Provides-Extra: test
Requires-Dist: playwright; extra == 'test'
Requires-Dist: pytest; extra == 'test'
Requires-Dist: pytest-asyncio; extra == 'test'
Requires-Dist: pytest-cov; extra == 'test'
Requires-Dist: pytest-jupyter[server]>=0.6.0; extra == 'test'
